cclip.py
cli_clip-0.1.1.dist-info/METADATA
cli_clip-0.1.1.dist-info/WHEEL
cli_clip-0.1.1.dist-info/entry_points.txt
cli_clip-0.1.1.dist-info/top_level.txt
cli_clip-0.1.1.dist-info/RECORD
