Metadata-Version: 2.4
Name: cli-clip
Version: 0.1.1
Project-URL: repository, https://github.com/Andrej730/cli-clip
Requires-Dist: pyperclip
Provides-Extra: test
Requires-Dist: pytest; extra == "test"
Provides-Extra: dev
Requires-Dist: poethepoet; extra == "dev"
Requires-Dist: black; extra == "dev"
Requires-Dist: ruff; extra == "dev"
Provides-Extra: build
Requires-Dist: build; extra == "build"
Requires-Dist: twine; extra == "build"
